ols_mcp/__init__.py
ols_mcp/__main__.py
ols_mcp/_version.py
ols_mcp/api.py
ols_mcp/main.py
ols_mcp/tools.py
ols_mcp-0.1.5.dist-info/METADATA
ols_mcp-0.1.5.dist-info/WHEEL
ols_mcp-0.1.5.dist-info/entry_points.txt
ols_mcp-0.1.5.dist-info/licenses/LICENSE
ols_mcp-0.1.5.dist-info/RECORD
