Metadata-Version: 2.4
Name: ols-mcp
Version: 0.1.5
Summary: MCP for retrieving things from the Ontology Lookup Service
Project-URL: Homepage, https://github.com/justaddcoffee/ols-mcp
Project-URL: Repository, https://github.com/justaddcoffee/ols-mcp
Project-URL: Issues, https://github.com/justaddcoffee/ols-mcp/issues
Project-URL: Documentation, https://github.com/justaddcoffee/ols-mcp#readme
Author-email: Justin Reese <justinreese@lbl.gov>
License: MIT License
License-File: LICENSE
Keywords: bioinformatics,mcp,ols,ontology
Classifier: Development Status :: 4 - Beta
Classifier: Intended Audience :: Developers
Classifier: Intended Audience :: Science/Research
Classifier: License :: OSI Approved :: MIT License
Classifier: Operating System :: OS Independent
Classifier: Programming Language :: Python :: 3
Classifier: Programming Language :: Python :: 3.11
Classifier: Programming Language :: Python :: 3.12
Classifier: Topic :: Scientific/Engineering
Classifier: Topic :: Software Development :: Libraries :: Python Modules
Requires-Python: >=3.11
Requires-Dist: fastmcp>=2.7.1
Requires-Dist: requests>=2.32.4
